sweetsweep/__init__.py
sweetsweep/__main__.py
sweetsweep/common.py
sweetsweep/mainwindow.ui
sweetsweep/sweep.py
sweetsweep/viewer.py
sweetsweep/icons/bold.png
sweetsweep/icons/font-size.png
sweetsweep/icons/white-bg.png
sweetsweep-0.1.6.dist-info/LICENSE
sweetsweep-0.1.6.dist-info/METADATA
sweetsweep-0.1.6.dist-info/WHEEL
sweetsweep-0.1.6.dist-info/top_level.txt
sweetsweep-0.1.6.dist-info/RECORD
