Metadata-Version: 2.1
Name: sweetsweep
Version: 0.1.6
Summary: SweetSweep: Run parameter sweeps and visualize results effortlessly
Author-email: Matthieu Heitz <heitz.matthieu@gmail.com>
Project-URL: Source code, https://github.com/matthieuheitz/sweet-sweep
Classifier: Programming Language :: Python :: 3
Classifier: License :: OSI Approved :: MIT License
Classifier: Operating System :: OS Independent
License-File: LICENSE
Requires-Dist: PyQt5
Requires-Dist: numpy
Requires-Dist: matplotlib
Provides-Extra: examples
Requires-Dist: matplotlib ; extra == 'examples'
Provides-Extra: parallel_sweep
Requires-Dist: pathos ; extra == 'parallel_sweep'
